LICENSE
MANIFEST.in
README.md
requirements.txt
setup.py
src/pii_extract_plg_transformers/__init__.py
src/pii_extract_plg_transformers/defs.py
src/pii_extract_plg_transformers/plugin_loader.py
src/pii_extract_plg_transformers.egg-info/PKG-INFO
src/pii_extract_plg_transformers.egg-info/SOURCES.txt
src/pii_extract_plg_transformers.egg-info/dependency_links.txt
src/pii_extract_plg_transformers.egg-info/entry_points.txt
src/pii_extract_plg_transformers.egg-info/requires.txt
src/pii_extract_plg_transformers.egg-info/top_level.txt
src/pii_extract_plg_transformers/app/__init__.py
src/pii_extract_plg_transformers/app/detect.py
src/pii_extract_plg_transformers/app/info.py
src/pii_extract_plg_transformers/resources/plugin-config.json
src/pii_extract_plg_transformers/task/__init__.py
src/pii_extract_plg_transformers/task/collector.py
src/pii_extract_plg_transformers/task/pipeline.py
src/pii_extract_plg_transformers/task/task.py
src/pii_extract_plg_transformers/task/utils.py